unisc/__init__.py
unisc/data/PropertyValueAliases.txt
unisc/data/ScriptExtensions.txt
unisc/data/Scripts.txt
unisc-0.1.dist-info/DESCRIPTION.rst
unisc-0.1.dist-info/METADATA
unisc-0.1.dist-info/RECORD
unisc-0.1.dist-info/WHEEL
unisc-0.1.dist-info/metadata.json
unisc-0.1.dist-info/top_level.txt
