Metadata-Version: 2.0
Name: unisc
Version: 0.1
Summary: Unicode Script property
Home-page: https://bitbucket.org/emptypage/unisc-python
Author: Masaaki Shibata
Author-email: mshibata@emptypage.jp
License: MIT
Keywords: property script script_extensions text unicode
Platform: UNKNOWN
Classifier: Development Status :: 3 - Alpha
Classifier: Intended Audience :: Developers
Classifier: License :: OSI Approved :: MIT License
Classifier: Operating System :: OS Independent
Classifier: Programming Language :: Python :: 3
Classifier: Programming Language :: Python :: 3.5
Classifier: Programming Language :: Python :: 3.6
Classifier: Topic :: Software Development :: Internationalization
Classifier: Topic :: Text Processing
Requires-Python: >=3.5
